<edmx:Edmx xmlns:edmx="http://docs.oasis-open.org/odata/ns/edmx" Version="4.0">
    <edmx:Reference Uri="https://sap.github.io/odata-vocabularies/vocabularies/Common.xml">
        <edmx:Include Namespace="com.sap.vocabularies.Common.v1" Alias="Common"/>
    </edmx:Reference>
    <edmx:Reference Uri="https://sap.github.io/odata-vocabularies/vocabularies/UI.xml">
        <edmx:Include Namespace="com.sap.vocabularies.UI.v1" Alias="UI"/>
    </edmx:Reference>
    <edmx:Reference Uri="/sap/opu/odata/sap/ZDMO_UI_DF_OPERATIONS_O2/$metadata">
        <edmx:Include Namespace="cds_zdmo_ui_df_operations"/>
    </edmx:Reference>
    <edmx:DataServices>
        <Schema xmlns="http://docs.oasis-open.org/odata/ns/edm" Namespace="nbs.poc.ovp.ui.app">
            <Annotations Target="cds_zdmo_ui_df_operations.OperationsType">
                <Annotation Term="UI.LineItem">
                    <Collection>
                        <Record Type="UI.DataField">
                            <PropertyValue Property="Label" String="Task ID"/>
                            <PropertyValue Property="Value" Path="TaskId"/>
                            <Annotation Term="UI.Importance" EnumMember="UI.ImportanceType/High"/>
                        </Record>
                        <Record Type="UI.DataField">
                            <PropertyValue Property="Label" String="Sales Order ID"/>
                            <PropertyValue Property="Value" Path="SalesOrderId"/>
                            <Annotation Term="UI.Importance" EnumMember="UI.ImportanceType/High"/>
                        </Record>
                        <Record Type="UI.DataField">
                            <PropertyValue Property="Label" String="Service Type"/>
                            <PropertyValue Property="Value" Path="ServiceType"/>
                            <Annotation Term="UI.Importance" EnumMember="UI.ImportanceType/High"/>
                        </Record>
                        <Record Type="UI.DataField">
                            <PropertyValue Property="Label" String="Ticket Owner"/>
                            <PropertyValue Property="Value" Path="TicketOwner"/>
                            <Annotation Term="UI.Importance" EnumMember="UI.ImportanceType/High"/>
                        </Record>
                        <Record Type="UI.DataField">
                            <PropertyValue Property="Label" String="Task Creation Date"/>
                            <PropertyValue Property="Value" Path="TaskCreationDate"/>
                            <Annotation Term="UI.Importance" EnumMember="UI.ImportanceType/High"/>
                        </Record>
                        <Record Type="UI.DataField">
                            <PropertyValue Property="Label" String="Task Due Date"/>
                            <PropertyValue Property="Value" Path="TaskDueDate"/>
                            <Annotation Term="UI.Importance" EnumMember="UI.ImportanceType/High"/>
                        </Record>
                        <Record Type="UI.DataField">
                            <PropertyValue Property="Label" String="Last Change Date"/>
                            <PropertyValue Property="Value" Path="LastChangeDate"/>
                            <Annotation Term="UI.Importance" EnumMember="UI.ImportanceType/High"/>
                        </Record>
                        <Record Type="UI.DataField">
                            <PropertyValue Property="Label" String="Vendor Quote Time"/>
                            <PropertyValue Property="Value" Path="Vendorquotetime"/>
                            <Annotation Term="UI.Importance" EnumMember="UI.ImportanceType/High"/>
                        </Record>
                        <Record Type="UI.DataField">
                            <PropertyValue Property="Value" Path="TaskId"/>
                            <Annotation Term="UI.Importance" EnumMember="UI.ImportanceType/High"/>
                        </Record>
                        <Record Type="UI.DataField">
                            <PropertyValue Property="Value" Path="SalesOrderId"/>
                            <Annotation Term="UI.Importance" EnumMember="UI.ImportanceType/High"/>
                        </Record>
                        <Record Type="UI.DataField">
                            <PropertyValue Property="Value" Path="ServiceType"/>
                            <Annotation Term="UI.Importance" EnumMember="UI.ImportanceType/High"/>
                        </Record>
                        <Record Type="UI.DataField">
                            <PropertyValue Property="Value" Path="TicketOwner"/>
                            <Annotation Term="UI.Importance" EnumMember="UI.ImportanceType/High"/>
                        </Record>
                        <Record Type="UI.DataField">
                            <PropertyValue Property="Value" Path="TaskCreationDate"/>
                            <Annotation Term="UI.Importance" EnumMember="UI.ImportanceType/High"/>
                        </Record>
                        <Record Type="UI.DataField">
                            <PropertyValue Property="Value" Path="TaskDueDate"/>
                            <Annotation Term="UI.Importance" EnumMember="UI.ImportanceType/High"/>
                        </Record>
                        <Record Type="UI.DataField">
                            <PropertyValue Property="Value" Path="Vendorquotetime"/>
                            <Annotation Term="UI.Importance" EnumMember="UI.ImportanceType/High"/>
                        </Record>
                        <Record Type="UI.DataField">
                            <PropertyValue Property="Value" Path="VendorquotetimeUom"/>
                            <Annotation Term="UI.Importance" EnumMember="UI.ImportanceType/High"/>
                        </Record>
                    </Collection>
                </Annotation>
                <Annotation Term="UI.Chart">
                    <Record Type="UI.ChartDefinitionType">
                        <PropertyValue Property="Title" String="Operations"/>
                        <PropertyValue Property="Description" String="REPLACE_WITH_CHART_DESCRIPTION"/>
                        <PropertyValue Property="ChartType" EnumMember="UI.ChartType/Column"/>
                        <PropertyValue Property="Dimensions">
                            <Collection>
                                <PropertyPath>TaskId</PropertyPath>
                            </Collection>
                        </PropertyValue>
                        <PropertyValue Property="Measures">
                            <Collection>
                                <PropertyPath>Vendorquotetime</PropertyPath>
                            </Collection>
                        </PropertyValue>
                    </Record>
                </Annotation>
                <Annotation Term="UI.PresentationVariant">
                    <Record Type="UI.PresentationVariantType">
                        <PropertyValue Property="Text" String="Default"/>
                        <PropertyValue Property="SortOrder">
                            <Collection>
                                <Record Type="Common.SortOrderType">
                                    <PropertyValue Property="Property" PropertyPath="Vendorquotetime"/>
                                    <PropertyValue Property="Descending" Bool="false"/>
                                </Record>
                            </Collection>
                        </PropertyValue>
                        <PropertyValue Property="IncludeGrandTotal" Bool="false"/>
                        <PropertyValue Property="InitialExpansionLevel" Int="1"/>
                        <PropertyValue Property="Visualizations">
                            <Collection>
                                <AnnotationPath>@UI.LineItem</AnnotationPath>
                                <AnnotationPath>@UI.Chart</AnnotationPath>
                            </Collection>
                        </PropertyValue>
                    </Record>
                </Annotation>
                <Annotation Term="UI.SelectionFields">
                    <Collection>
                        <PropertyPath>TaskId</PropertyPath>
                        <PropertyPath>TicketOwner</PropertyPath>
                        <PropertyPath>TaskDueDate</PropertyPath>
                        <PropertyPath>TaskId</PropertyPath>
                        <PropertyPath>SalesOrderId</PropertyPath>
                        <PropertyPath>ServiceType</PropertyPath>
                        <PropertyPath>TicketOwner</PropertyPath>
                        <PropertyPath>TaskDueDate</PropertyPath>
                    </Collection>
                </Annotation>
                <Annotation Term="UI.Chart" Qualifier="ChFilterQuanByServiceType">
                    <Record Type="UI.ChartDefinitionType">
                        <PropertyValue Property="Title" String="Quantity By Service Type"/>
                        <PropertyValue Property="Description" String="Quantity By Service Type"/>
                        <PropertyValue Property="ChartType" EnumMember="UI.ChartType/Bar"/>
                        <PropertyValue Property="Dimensions">
                            <Collection>
                                <PropertyPath>ServiceType</PropertyPath>
                            </Collection>
                        </PropertyValue>
                        <PropertyValue Property="Measures">
                            <Collection>
                                <PropertyPath>Vendorquotetime</PropertyPath>
                            </Collection>
                        </PropertyValue>
                    </Record>
                </Annotation>
                <Annotation Term="UI.PresentationVariant" Qualifier="PVFilterQuanByServiceType">
                    <Record Type="UI.PresentationVariantType">
                        <PropertyValue Property="Visualizations">
                            <Collection>
                                <AnnotationPath>@UI.Chart#ChFilterQuanByServiceType</AnnotationPath>
                            </Collection>
                        </PropertyValue>
                    </Record>
                </Annotation>
                <Annotation Term="UI.Chart" Qualifier="ChFilterQuanByTicketOwner">
                    <Record Type="UI.ChartDefinitionType">
                        <PropertyValue Property="Title" String="Quantity By Ticket Owner"/>
                        <PropertyValue Property="Description" String="Quantity By Ticket Owner"/>
                        <PropertyValue Property="ChartType" EnumMember="UI.ChartType/Donut"/>
                        <PropertyValue Property="Dimensions">
                            <Collection>
                                <PropertyPath>TicketOwner</PropertyPath>
                            </Collection>
                        </PropertyValue>
                        <PropertyValue Property="Measures">
                            <Collection>
                                <PropertyPath>Vendorquotetime</PropertyPath>
                            </Collection>
                        </PropertyValue>
                    </Record>
                </Annotation>
                <Annotation Term="UI.PresentationVariant" Qualifier="PVFilterQuanByTicketOwner">
                    <Record Type="UI.PresentationVariantType">
                        <PropertyValue Property="Visualizations">
                            <Collection>
                                <AnnotationPath>@UI.Chart#ChFilterQuanByTicketOwner</AnnotationPath>
                            </Collection>
                        </PropertyValue>
                    </Record>
                </Annotation>
                <Annotation Term="UI.Chart" Qualifier="ChFilterByDate">
                    <Record Type="UI.ChartDefinitionType">
                        <PropertyValue Property="Title" String="Filter By Due Date"/>
                        <PropertyValue Property="Description" String="Filter By Due Date"/>
                        <PropertyValue Property="ChartType" EnumMember="UI.ChartType/Line"/>
                        <PropertyValue Property="Dimensions">
                            <Collection>
                                <PropertyPath>TaskDueDate</PropertyPath>
                            </Collection>
                        </PropertyValue>
                        <PropertyValue Property="Measures">
                            <Collection>
                                <PropertyPath>Vendorquotetime</PropertyPath>
                            </Collection>
                        </PropertyValue>
                    </Record>
                </Annotation>
                <Annotation Term="UI.PresentationVariant" Qualifier="PVFilterByDate">
                    <Record Type="UI.PresentationVariantType">
                        <PropertyValue Property="Visualizations">
                            <Collection>
                                <AnnotationPath>@UI.Chart#ChFilterByDate</AnnotationPath>
                            </Collection>
                        </PropertyValue>
                    </Record>
                </Annotation>
            </Annotations>
            <Annotations Target="cds_zdmo_ui_df_operations.OperationsType/ServiceType">
                <Annotation Term="Common.ValueList">
                    <Record Type="Common.ValueListType">
                        <PropertyValue Property="CollectionPath" String="Operations"/>
                        <PropertyValue Property="PresentationVariantQualifier" String="PVFilterQuanByServiceType"/>
                        <PropertyValue Property="Parameters">
                            <Collection>
                                <Record Type="Common.ValueListParameterInOut">
                                    <PropertyValue Property="LocalDataProperty" PropertyPath="ServiceType"/>
                                    <PropertyValue Property="ValueListProperty" String="ServiceType"/>
                                </Record>
                            </Collection>
                        </PropertyValue>
                    </Record>
                </Annotation>
            </Annotations>
            <Annotations Target="cds_zdmo_ui_df_operations.OperationsType/TicketOwner">
                <Annotation Term="Common.ValueList">
                    <Record Type="Common.ValueListType">
                        <PropertyValue Property="CollectionPath" String="Operations"/>
                        <PropertyValue Property="PresentationVariantQualifier" String="PVFilterQuanByTicketOwner"/>
                        <PropertyValue Property="Parameters">
                            <Collection>
                                <Record Type="Common.ValueListParameterInOut">
                                    <PropertyValue Property="LocalDataProperty" PropertyPath="TicketOwner"/>
                                    <PropertyValue Property="ValueListProperty" String="TicketOwner"/>
                                </Record>
                            </Collection>
                        </PropertyValue>
                    </Record>
                </Annotation>
            </Annotations>
            <Annotations Target="cds_zdmo_ui_df_operations.OperationsType/TaskDueDate">
                <Annotation Term="Common.ValueList">
                    <Record Type="Common.ValueListType">
                        <PropertyValue Property="CollectionPath" String="Operations"/>
                        <PropertyValue Property="PresentationVariantQualifier" String="PVFilterByDate"/>
                        <PropertyValue Property="Parameters">
                            <Collection>
                                <Record Type="Common.ValueListParameterInOut">
                                    <PropertyValue Property="LocalDataProperty" PropertyPath="TaskDueDate"/>
                                    <PropertyValue Property="ValueListProperty" String="TaskDueDate"/>
                                </Record>
                            </Collection>
                        </PropertyValue>
                    </Record>
                </Annotation>
            </Annotations>
        </Schema>
    </edmx:DataServices>
</edmx:Edmx>